setup.py
python_tests_web/__init__.py
python_tests_web/dependencies_node.py
python_tests_web.egg-info/PKG-INFO
python_tests_web.egg-info/SOURCES.txt
python_tests_web.egg-info/dependency_links.txt
python_tests_web.egg-info/requires.txt
python_tests_web.egg-info/top_level.txt