Metadata-Version: 2.1
Name: python-tests-web
Version: 0.5
Summary: A simple functional test library using Selenium and Chrome driver
Home-page: UNKNOWN
Author: Linda Lopez
License: UNKNOWN
Platform: UNKNOWN
Classifier: Development Status :: 3 - Alpha
Classifier: Intended Audience :: Developers
Classifier: License :: OSI Approved :: MIT License
Classifier: Programming Language :: Python
